ewokstomo/__init__.py
ewokstomo/tasks/__init__.py
ewokstomo/tasks/buildgallery.py
ewokstomo/tasks/dataportalupload.py
ewokstomo/tasks/energycalculation.py
ewokstomo/tasks/nxtomomill.py
ewokstomo/tasks/reconstruct_slice.py
ewokstomo/tasks/reducedarkflat.py
ewokstomo/tasks/utils.py
ewokstomo/tasks/online/__init__.py
ewokstomo/tasks/online/preprocessing.py
ewokstomo/tasks/online/reconstruct_slice.py
ewokstomo/tasks/online/reducedarkflat.py
ewokstomo/tests/__init__.py
ewokstomo/tests/test_dataportalupload.py
ewokstomo/tests/test_energycalculation.py
ewokstomo/tests/test_gallery.py
ewokstomo/tests/test_nxtomomill.py
ewokstomo/tests/test_reconstructslice.py
ewokstomo/tests/test_reducedarkflat.py
ewokstomo/tests/test_utils.py
ewokstomo/tests/data/PROCESSED_DATA/TestEwoksTomo/TestEwoksTomo_0010/projections/TestEwoksTomo_0010.nx
ewokstomo/tests/data/PROCESSED_DATA/TestEwoksTomo/TestEwoksTomo_0010/projections/TestEwoksTomo_0010_0000.nx
ewokstomo/tests/data/PROCESSED_DATA/TestEwoksTomo/TestEwoksTomo_0010/slices/TestEwoksTomo_0010slice_000008_plane_XY/TestEwoksTomo_0010slice_000008_plane_XY_00008.hdf5
ewokstomo/tests/data/RAW_DATA/TestEwoksTomo/SiemensLH_aligned_33keV_0002/SiemensLH_aligned_33keV_0002.h5
ewokstomo/tests/data/RAW_DATA/TestEwoksTomo/TestEwoksTomo_0010/TestEwoksTomo_0010.h5
ewokstomo/tests/data/RAW_DATA/TestEwoksTomo/TestEwoksTomo_0010/scan0002/edgetwinmic_0000.h5
ewokstomo/tests/data/RAW_DATA/TestEwoksTomo/TestEwoksTomo_0010/scan0003/edgetwinmic_0000.h5
ewokstomo/tests/data/RAW_DATA/TestEwoksTomo/TestEwoksTomo_0010/scan0004/edgetwinmic_0000.h5
ewokstomo/tests/data/RAW_DATA/TestEwoksTomo/TestEwoksTomo_0010/scan0004/edgetwinmic_0001.h5
ewokstomo/tests/data/RAW_DATA/TestEwoksTomo/TestEwoksTomo_0010/scan0004/edgetwinmic_0002.h5
ewokstomo/tests/data/RAW_DATA/TestEwoksTomo/TestEwoksTomo_0010/scan0004/edgetwinmic_0003.h5
ewokstomo/tests/data/RAW_DATA/TestEwoksTomo/TestEwoksTomo_0010/scan0004/edgetwinmic_0004.h5
ewokstomo-0.6.0.dist-info/licenses/LICENSE
ewokstomo-0.6.0.dist-info/METADATA
ewokstomo-0.6.0.dist-info/WHEEL
ewokstomo-0.6.0.dist-info/entry_points.txt
ewokstomo-0.6.0.dist-info/top_level.txt
ewokstomo-0.6.0.dist-info/RECORD
