Metadata-Version: 2.4
Name: ewokstomo
Version: 0.6.0
Summary: Data processing workflows for Tomography
Author-email: ESRF <dau-pydev@esrf.fr>
License-Expression: MIT
Project-URL: Homepage, https://gitlab.esrf.fr/workflow/ewoksapps/ewokstomo/
Project-URL: Documentation, https://ewokstomo.readthedocs.io/
Project-URL: Repository, https://gitlab.esrf.fr/workflow/ewoksapps/ewokstomo/
Project-URL: Issues, https://gitlab.esrf.fr/workflow/ewoksapps/ewokstomo/issues
Project-URL: Changelog, https://gitlab.esrf.fr/workflow/ewoksapps/ewokstomo/-/blob/main/CHANGELOG.md
Keywords: ewoks
Classifier: Intended Audience :: Science/Research
Classifier: Programming Language :: Python :: 3
Classifier: Programming Language :: Python :: 3.10
Classifier: Programming Language :: Python :: 3.11
Classifier: Programming Language :: Python :: 3.12
Classifier: Programming Language :: Python :: 3.13
Requires-Python: >=3.10
License-File: LICENSE
Requires-Dist: blissdata
Requires-Dist: ewokscore
Requires-Dist: nxtomomill
Requires-Dist: pyicat_plus
Requires-Dist: tomoscan
Requires-Dist: nabu
Requires-Dist: pyopencl[pocl]
Requires-Dist: esrf-pathlib==0.6.0
Requires-Dist: esrf_ontologies
Requires-Dist: xraylib
Requires-Dist: xoppylib
Provides-Extra: test
Requires-Dist: pytest>=7; extra == "test"
Requires-Dist: nabu[full_nocuda]; extra == "test"
Requires-Dist: ewoks; extra == "test"
Requires-Dist: pytest-order; extra == "test"
Provides-Extra: no-cuda
Requires-Dist: ewokstomo; extra == "no-cuda"
Requires-Dist: nabu[full_nocuda]; extra == "no-cuda"
Provides-Extra: cuda
Requires-Dist: ewokstomo; extra == "cuda"
Requires-Dist: nabu[full]; extra == "cuda"
Provides-Extra: dev
Requires-Dist: ewokstomo[test]; extra == "dev"
Requires-Dist: black>=25; extra == "dev"
Requires-Dist: flake8>=4; extra == "dev"
Requires-Dist: ruff>=0.4; extra == "dev"
Requires-Dist: bandit>=1.7; extra == "dev"
Provides-Extra: doc
Requires-Dist: ewokstomo; extra == "doc"
Requires-Dist: ewoks; extra == "doc"
Requires-Dist: sphinx>=4.5; extra == "doc"
Requires-Dist: ewokssphinx>=1.0.0; extra == "doc"
Requires-Dist: sphinx-autodoc-typehints>=1.16; extra == "doc"
Requires-Dist: pydata-sphinx-theme; extra == "doc"
Requires-Dist: sphinx-copybutton; extra == "doc"
Requires-Dist: myst-parser; extra == "doc"
Dynamic: license-file
